dask_geomodeling/__init__.py
dask_geomodeling/config.py
dask_geomodeling/ipyleaflet_plugin.py
dask_geomodeling/measurements.py
dask_geomodeling/utils.py
dask_geomodeling/core/__init__.py
dask_geomodeling/core/graphs.py
dask_geomodeling/geometry/__init__.py
dask_geomodeling/geometry/aggregate.py
dask_geomodeling/geometry/base.py
dask_geomodeling/geometry/constructive.py
dask_geomodeling/geometry/field_operations.py
dask_geomodeling/geometry/geom_operations.py
dask_geomodeling/geometry/merge.py
dask_geomodeling/geometry/parallelize.py
dask_geomodeling/geometry/set_operations.py
dask_geomodeling/geometry/sinks.py
dask_geomodeling/geometry/sources.py
dask_geomodeling/geometry/text.py
dask_geomodeling/raster/__init__.py
dask_geomodeling/raster/base.py
dask_geomodeling/raster/combine.py
dask_geomodeling/raster/elemwise.py
dask_geomodeling/raster/misc.py
dask_geomodeling/raster/parallelize.py
dask_geomodeling/raster/reduction.py
dask_geomodeling/raster/sources.py
dask_geomodeling/raster/spatial.py
dask_geomodeling/raster/temporal.py
dask_geomodeling/tests/__init__.py
dask_geomodeling/tests/conftest.py
dask_geomodeling/tests/factories.py
dask_geomodeling/tests/test_aggregate_raster.py
dask_geomodeling/tests/test_core.py
dask_geomodeling/tests/test_geometry.py
dask_geomodeling/tests/test_geometry_sinks.py
dask_geomodeling/tests/test_measurements.py
dask_geomodeling/tests/test_raster.py
dask_geomodeling/tests/test_raster_elemwise.py
dask_geomodeling/tests/test_raster_misc.py
dask_geomodeling/tests/test_raster_parallelize.py
dask_geomodeling/tests/test_raster_reduction.py
dask_geomodeling/tests/test_raster_sources.py
dask_geomodeling/tests/test_raster_spatial.py
dask_geomodeling/tests/test_raster_temporal.py
dask_geomodeling/tests/test_utils.py
dask_geomodeling-2.7.0.dist-info/METADATA
dask_geomodeling-2.7.0.dist-info/WHEEL
dask_geomodeling-2.7.0.dist-info/licenses/LICENSE
dask_geomodeling-2.7.0.dist-info/RECORD
