Metadata-Version: 2.4
Name: dask-geomodeling
Version: 2.7.0
Summary: On-the-fly operations on geographical maps.
Project-URL: Homepage, https://github.com/nens/dask-geomodeling
Author-email: Nelen & Schuurmans <info@nelen-schuurmans.nl>
License-Expression: BSD-3-Clause
License-File: LICENSE
Keywords: dask
Classifier: Development Status :: 4 - Beta
Classifier: Operating System :: OS Independent
Classifier: Programming Language :: Python :: 3 :: Only
Classifier: Topic :: Scientific/Engineering :: GIS
Requires-Python: >=3.10
Requires-Dist: dask[delayed]>=2022
Requires-Dist: geopandas>=1
Requires-Dist: numpy>=1.23
Requires-Dist: packaging
Requires-Dist: pandas>=2
Requires-Dist: pyogrio
Requires-Dist: pytz
Requires-Dist: scipy>=1.11
Provides-Extra: cityhash
Requires-Dist: cityhash; extra == 'cityhash'
Provides-Extra: test
Requires-Dist: pytest; extra == 'test'
